Workbook

Sheet Léeme
A1: Modelo de precios — logistika
A2: Cómo se usa este libro y qué significa cada color
A5: QUÉ ES ESTO
B6: Para qué sirve | C6: Calcula bandas de precio para los productos de logistika a partir de la capacidad real de Adriana y de su ingreso objetivo. No son precios de mercado: son el piso por debajo del cual el trabajo pierde dinero, y el objetivo que hace que el negocio valga la pena.
B7: Qué NO es | C7: No es un estudio de mercado. Nadie ha cotizado a la competencia todavía. Antes de publicar un precio hay que contrastarlo (ver la hoja 'Validación de mercado').
B8: Moneda | C8: Todo en pesos mexicanos. La hoja 'Supuestos' tiene el tipo de cambio para cotizar en dólares a clientes extranjeros.
A10: CÓMO SE USA
B11: 1. Supuestos | C11: Edita SOLO las celdas amarillas. Son las horas que Adriana puede dedicar, lo que quiere ganar y sus costos fijos. Todo lo demás se recalcula solo.
B12: 2. Horas por producto | C12: Ajusta las horas estimadas de cada entregable. Es el supuesto que más mueve el precio y el que Adriana puede corregir mejor que nadie.
B13: 3. Bandas de precio | C13: Sale el resultado: piso, objetivo y premium por producto. De ahí se elige lo que se publica.
B14: 4. Capacidad | C14: Comprueba cuántos clientes caben en sus horas. Esta hoja es la que dice si PARTNER se puede lanzar o no.
B15: 5. Matriz | C15: Qué servicio entra en qué nivel. Es lo que va publicado en el sitio.
A17: COLORES
B18: Amarillo con letra azul | C18: Dato que capturas tú. Son los únicos que debes tocar.
B19: Letra negra | C19: Fórmula. Si la sobrescribes, el modelo deja de recalcularse.
B20: Letra verde | C20: Trae un valor de otra hoja.
A22: ADVERTENCIA
B23: Los supuestos son míos | C23: Las horas por entregable y los costos fijos son estimaciones razonadas, no datos que Adriana me haya dado. Cada una tiene su justificación escrita al lado. Revísalas una por una antes de usar cualquier número de salida: si las horas están mal, el precio está mal, por muy bien que calcule el libro.

Sheet Supuestos
A1: Supuestos
A2: Edita solo las celdas amarillas. Todo lo demás se calcula.
B4: CAPACIDAD
B5: Horas por semana dedicables a logistika | C5: 12 | D5: Adriana tiene un trabajo de tiempo completo. 12 h/semana son ~2 h entre semana más medio sábado. Si esto sube, sube todo lo demás.
B6: Semanas facturables al año | C6: 44 | D6: 52 menos vacaciones, puentes y las semanas muertas de diciembre.
B7: % de horas no facturables (venta, propuestas, admin) | C7: 0.35 | D7: En consultoría independiente, un tercio del tiempo se va en conseguir el trabajo, no en hacerlo. Con 0.20 el modelo se vuelve optimista.
B8: Horas facturables al año | C8: =C5*C6*(1-C7) -> 343.2 | D8: Este es el número que limita todo el negocio.
B10: ECONOMÍA
B11: Ingreso anual objetivo de logistika (MXN) | C11: 480000 | D11: Lo que Adriana quiere que le deje logistika al año, ADEMÁS de su sueldo. Cámbialo por su cifra real: es el supuesto más importante del libro.
B12: Costos fijos anuales (MXN) | C12: 60000 | D12: Contador, software, seguro de responsabilidad, sitio, telefonía, membresías de cámara. Estimación mía, no un presupuesto suyo.
B13: Margen objetivo sobre el piso | C13: 0.35 | D13: Colchón para reinversión, cuentas incobrables y trabajo no cobrado. Por debajo de 0.25 no queda margen para errores de estimación.
B14: Factor premium (precio por valor) | C14: 1.35 | D14: Se aplica donde el valor para el cliente es mucho mayor que las horas invertidas, como el diagnóstico. No se aplica a trabajo por volumen.
B16: TARIFAS DERIVADAS
B17: Costo por hora facturable (piso) | C17: =IFERROR((C11+C12)/C8,0) -> 1573.4266 | D17: Por debajo de esto, cada hora trabajada le cuesta dinero.
B18: Tarifa objetivo por hora | C18: =IFERROR(C17/(1-C13),0) -> 2420.6563 | D18: Piso más el margen objetivo. Es la tarifa con la que se debe cotizar.
B19: Tarifa premium por hora | C19: =C18*C14 -> 3267.886
B21: TIPO DE CAMBIO
B22: MXN por USD | C22: 18.5 | D22: CONFIRMAR antes de cotizar en dólares. Este número se mueve todas las semanas; el que está aquí es un marcador, no una cotización.

Sheet Horas por producto
A1: Horas estimadas por entregable
A2: El supuesto que más mueve el precio. Ajústalo con la experiencia de Adriana.
B4: Producto | C4: Qué incluye | D4: Horas optimista | E4: Horas base | F4: Horas pesimista | G4: Horas ponderadas | H4: Justificación del rango
B5: Health Check | C5: Diagnóstico de cadena de suministro (10–15 días) | D5: 10 | E5: 16 | F5: 26 | G5: =(D5+4*E5+F5)/6 -> 16.666667 | H5: Entrevistas, revisión documental, análisis de costos, redacción del reporte y presentación. El rango alto es una operación con varios proveedores y sin datos ordenados.
B6: START | C6: Consultoría y plan de importación | D6: 14 | E6: 22 | F6: 34 | G6: =(D6+4*E6+F6)/6 -> 22.666667 | H6: Análisis de producto, proveedor y origen; clasificación arancelaria; costo en destino; régimen y ruta; expediente de viabilidad.
B7: MANAGE — arranque | C7: Alta de cuenta: procedimientos, formatos, alta de proveedores | D7: 8 | E7: 14 | F7: 22 | G7: =(D7+4*E7+F7)/6 -> 14.333333 | H7: Trabajo de una sola vez al iniciar la relación. Se cobra aparte o se amortiza en los primeros tres meses.
B8: MANAGE — mensual | C8: Coordinación mensual base (sin embarques) | D8: 3 | E8: 5 | F8: 8 | G8: =(D8+4*E8+F8)/6 -> 5.1666667 | H8: Junta de seguimiento, reporte de indicadores, auditoría de facturas de proveedores.
B9: MANAGE — por embarque | C9: Coordinación de un embarque de punta a punta | D9: 1.5 | E9: 2.5 | F9: 4.5 | G9: =(D9+4*E9+F9)/6 -> 2.6666667 | H9: Revisión documental previa, coordinación con forwarder y agente, seguimiento de ETA, liberación, entrega y cierre de expediente.
B10: PARTNER — mensual | C10: Departamento externo de comercio exterior | D10: 18 | E10: 28 | F10: 40 | G10: =(D10+4*E10+F10)/6 -> 28.333333 | H10: Incluye todo MANAGE más exportaciones, abastecimiento, cumplimiento y reporte a dirección. OJO: son horas que Adriana hoy no tiene.
B12: Las horas ponderadas usan PERT: (optimista + 4×base + pesimista) / 6. Un promedio simple subestima el trabajo de coordinación, porque lo que sale mal siempre cuesta más de lo que se ahorra cuando sale bien.

Sheet Bandas de precio
A1: Bandas de precio por producto
A2: Salida del modelo. Nada aquí se captura a mano.
B4: Producto | C4: Horas ponderadas | D4: Piso (MXN) | E4: Objetivo (MXN) | F4: Premium (MXN) | G4: Objetivo (USD) | H4: Cómo se cobra
B5: Health Check | C5: ='Horas por producto'!G5 -> 16.666667 | D5: =C5*Supuestos!$C$17 -> 26223.776 | E5: =C5*Supuestos!$C$18 -> 40344.271 | F5: =C5*Supuestos!$C$19 -> 54464.766 | G5: =IFERROR(E5/Supuestos!$C$22,0) -> 2180.7714 | H5: Precio fijo, 50% al inicio y 50% contra entrega
B6: START | C6: ='Horas por producto'!G6 -> 22.666667 | D6: =C6*Supuestos!$C$17 -> 35664.336 | E6: =C6*Supuestos!$C$18 -> 54868.209 | F6: =C6*Supuestos!$C$19 -> 74072.082 | G6: =IFERROR(E6/Supuestos!$C$22,0) -> 2965.8491 | H6: Precio fijo por proyecto
B7: MANAGE — arranque | C7: ='Horas por producto'!G7 -> 14.333333 | D7: =C7*Supuestos!$C$17 -> 22552.448 | E7: =C7*Supuestos!$C$18 -> 34696.073 | F7: =C7*Supuestos!$C$19 -> 46839.699 | G7: =IFERROR(E7/Supuestos!$C$22,0) -> 1875.4634 | H7: Único, al firmar
B8: MANAGE — mensual | C8: ='Horas por producto'!G8 -> 5.1666667 | D8: =C8*Supuestos!$C$17 -> 8129.3706 | E8: =C8*Supuestos!$C$18 -> 12506.724 | F8: =C8*Supuestos!$C$19 -> 16884.077 | G8: =IFERROR(E8/Supuestos!$C$22,0) -> 676.03914 | H8: Iguala mensual
B9: MANAGE — por embarque | C9: ='Horas por producto'!G9 -> 2.6666667 | D9: =C9*Supuestos!$C$17 -> 4195.8042 | E9: =C9*Supuestos!$C$18 -> 6455.0834 | F9: =C9*Supuestos!$C$19 -> 8714.3626 | G9: =IFERROR(E9/Supuestos!$C$22,0) -> 348.92343 | H9: Fee por embarque, se suma a la iguala
B10: PARTNER — mensual | C10: ='Horas por producto'!G10 -> 28.333333 | D10: =C10*Supuestos!$C$17 -> 44580.42 | E10: =C10*Supuestos!$C$18 -> 68585.261 | F10: =C10*Supuestos!$C$19 -> 92590.102 | G10: =IFERROR(E10/Supuestos!$C$22,0) -> 3707.3114 | H10: Iguala mensual, contrato anual
B12: PAQUETE MANAGE — lo que factura un cliente típico
B13: Embarques al mes de un cliente promedio | C13: 12 | D13: Rango objetivo del nivel MANAGE: entre 5 y 30 embarques al mes.
B14: Iguala mensual (objetivo) | C14: =E8 -> 12506.724
B15: Fee por embarque (objetivo) | C15: =E9 -> 6455.0834
B16: Facturación mensual de ese cliente | C16: =C14+C13*C15 -> 89967.725
B17: Horas que ese cliente consume al mes | C17: ='Horas por producto'!G8+C13*'Horas por producto'!G9 -> 37.166667
B19: El precio de salida es el OBJETIVO, no el piso. El piso solo sirve para saber cuándo hay que decir que no: si un cliente regatea por debajo de esa columna, el trabajo cuesta dinero en vez de generarlo.

Sheet Capacidad
A1: ¿Cuánto cabe en las horas de Adriana?
A2: La restricción de este negocio es el tiempo, no la demanda. Esta hoja decide qué se lanza.
B4: HORAS DISPONIBLES
B5: Horas facturables al año | C5: =Supuestos!C8 -> 343.2
B6: Horas facturables al mes | C6: =C5/12 -> 28.6
B8: LO QUE CONSUME CADA CLIENTE AL MES
B9: Un cliente MANAGE, al volumen supuesto | C9: ='Bandas de precio'!C17 -> 37.166667
B10: Un cliente PARTNER | C10: ='Horas por producto'!G10 -> 28.333333
B12: CUÁNTOS CABEN
B13: Clientes MANAGE simultáneos | C13: =IFERROR(C6/C9,0) -> 0.76950673 | D13: =IF(C13<1,"NO CABE NI UNO. Al volumen supuesto, un solo cliente MANAGE pide más horas de las que hay en el mes.","Caben "&TEXT(C13,"0.0")&". Redondea hacia abajo.") -> NO CABE NI UNO. Al volumen supuesto, un solo cliente MANAGE pide más horas de las que hay en el mes.
B14: Clientes PARTNER simultáneos | C14: =IFERROR(C6/C10,0) -> 1.0094118 | D14: =IF(C14<1,"NO CABE. Lanzar solo START y MANAGE.","Cabe justo "&TEXT(C14,"0.00")&"x: sin margen para un imprevisto ni para vender el siguiente proyecto.") -> Cabe justo 1.01x: sin margen para un imprevisto ni para vender el siguiente proyecto.
B16: EL LÍMITE REAL DE MANAGE
B17: Horas que quedan tras la iguala base | C17: =C6-'Horas por producto'!G8 -> 23.433333
B18: Embarques al mes que caben en esas horas | C18: =IFERROR(C17/'Horas por producto'!G9,0) -> 8.7875 | D18: Máximo absoluto para UN cliente, consumiendo el 100% de las horas. Para operar con holgura, la mitad.
B19: Volumen supuesto en 'Bandas de precio' | C19: ='Bandas de precio'!C13 -> 12 | D19: =IF(C19>C18,"El volumen supuesto NO cabe. Baja el volumen, sube las horas disponibles, o no vendas MANAGE todavía.","El volumen supuesto cabe.") -> El volumen supuesto NO cabe. Baja el volumen, sube las horas disponibles, o no vendas MANAGE todavía.
B21: INGRESO ALCANZABLE (limitado por capacidad)
B22: Clientes MANAGE que se quisieran sostener | C22: 2 | D22: Lo que se desea. La línea de abajo lo recorta a lo que cabe.
B23: Clientes que realmente caben | C23: =MIN(C22,INT(C13)) -> 0 | D23: Se toma el menor entre lo deseado y lo posible. Aquí es donde el plan se topa con el calendario.
B24: Facturación anual con esa cartera | C24: ='Bandas de precio'!C16*C23*12 -> 0
B25: Ingreso objetivo | C25: =Supuestos!C11 -> 480000
B26: Diferencia contra el objetivo | C26: =C24-C25 -> -480000 | D26: =IF(C23=0,"Con esta capacidad no cabe ningún cliente MANAGE: el ingreso tiene que venir de diagnósticos y proyectos START.",IF(C26<0,"Falta. Sube precio, sube horas o baja el objetivo.","El objetivo se alcanza.")) -> Con esta capacidad no cabe ningún cliente MANAGE: el ingreso tiene que venir de diagnósticos y proyectos START.
B28: LA RUTA QUE SÍ CABE
B29: Diagnósticos (Health Check) al año | C29: 8 | D29: Uno cada mes y medio. Es el producto de entrada y el que mejor paga por hora.
B30: Proyectos START al año | C30: 4 | D30: Uno por trimestre, normalmente derivado de un diagnóstico previo.
B31: Horas que consume ese plan | C31: =C29*'Horas por producto'!G5+C30*'Horas por producto'!G6 -> 224
B32: Contra las horas disponibles al año | C32: =C5 -> 343.2
B33: Horas libres restantes | C33: =C32-C31 -> 119.2
B34: Facturación anual de ese plan | C34: =C29*'Bandas de precio'!E5+C30*'Bandas de precio'!E6 -> 542227
B35: Contra el objetivo | C35: =C34-Supuestos!C11 -> 62227.004 | D35: =IF(C33<0,"Este plan tampoco cabe: baja el número de proyectos.",IF(C35>=0,"Este plan alcanza el objetivo Y deja "&TEXT(C33,"0")&" horas libres para un cliente recurrente.","No alcanza el objetivo, pero cabe. Suma proyectos o sube precio.")) -> Este plan alcanza el objetivo Y deja 119 horas libres para un cliente recurrente.
B37: Lectura del modelo: con capacidad de medio tiempo, el trabajo por volumen (coordinar muchos embarques) es el peor negocio por hora, y además es el que más se parece a un empleo. Los diagnósticos y los proyectos de precio fijo pagan mucho mejor la hora y se pueden agendar. Esa es la razón de arrancar por ahí, no un capricho de posicionamiento.

Sheet Sensibilidad
A1: Qué pasa si cambian las horas disponibles y el margen
A2: Tarifa objetivo por hora (MXN) para cada combinación.
B4: Horas / semana ↓ Margen → | C4: 0.2 | D4: 0.28 | E4: 0.35 | F4: 0.42 | G4: 0.5
B5: 6 | C5: =IFERROR((Supuestos!$C$11+Supuestos!$C$12)/($B5*Supuestos!$C$6*(1-Supuestos!$C$7))/(1-C$4),0) -> 3933.5664 | D5: =IFERROR((Supuestos!$C$11+Supuestos!$C$12)/($B5*Supuestos!$C$6*(1-Supuestos!$C$7))/(1-D$4),0) -> 4370.6294 | E5: =IFERROR((Supuestos!$C$11+Supuestos!$C$12)/($B5*Supuestos!$C$6*(1-Supuestos!$C$7))/(1-E$4),0) -> 4841.3125 | F5: =IFERROR((Supuestos!$C$11+Supuestos!$C$12)/($B5*Supuestos!$C$6*(1-Supuestos!$C$7))/(1-F$4),0) -> 5425.6089 | G5: =IFERROR((Supuestos!$C$11+Supuestos!$C$12)/($B5*Supuestos!$C$6*(1-Supuestos!$C$7))/(1-G$4),0) -> 6293.7063
B6: 9 | C6: =IFERROR((Supuestos!$C$11+Supuestos!$C$12)/($B6*Supuestos!$C$6*(1-Supuestos!$C$7))/(1-C$4),0) -> 2622.3776 | D6: =IFERROR((Supuestos!$C$11+Supuestos!$C$12)/($B6*Supuestos!$C$6*(1-Supuestos!$C$7))/(1-D$4),0) -> 2913.7529 | E6: =IFERROR((Supuestos!$C$11+Supuestos!$C$12)/($B6*Supuestos!$C$6*(1-Supuestos!$C$7))/(1-E$4),0) -> 3227.5417 | F6: =IFERROR((Supuestos!$C$11+Supuestos!$C$12)/($B6*Supuestos!$C$6*(1-Supuestos!$C$7))/(1-F$4),0) -> 3617.0726 | G6: =IFERROR((Supuestos!$C$11+Supuestos!$C$12)/($B6*Supuestos!$C$6*(1-Supuestos!$C$7))/(1-G$4),0) -> 4195.8042
B7: 12 | C7: =IFERROR((Supuestos!$C$11+Supuestos!$C$12)/($B7*Supuestos!$C$6*(1-Supuestos!$C$7))/(1-C$4),0) -> 1966.7832 | D7: =IFERROR((Supuestos!$C$11+Supuestos!$C$12)/($B7*Supuestos!$C$6*(1-Supuestos!$C$7))/(1-D$4),0) -> 2185.3147 | E7: =IFERROR((Supuestos!$C$11+Supuestos!$C$12)/($B7*Supuestos!$C$6*(1-Supuestos!$C$7))/(1-E$4),0) -> 2420.6563 | F7: =IFERROR((Supuestos!$C$11+Supuestos!$C$12)/($B7*Supuestos!$C$6*(1-Supuestos!$C$7))/(1-F$4),0) -> 2712.8044 | G7: =IFERROR((Supuestos!$C$11+Supuestos!$C$12)/($B7*Supuestos!$C$6*(1-Supuestos!$C$7))/(1-G$4),0) -> 3146.8531
B8: 16 | C8: =IFERROR((Supuestos!$C$11+Supuestos!$C$12)/($B8*Supuestos!$C$6*(1-Supuestos!$C$7))/(1-C$4),0) -> 1475.0874 | D8: =IFERROR((Supuestos!$C$11+Supuestos!$C$12)/($B8*Supuestos!$C$6*(1-Supuestos!$C$7))/(1-D$4),0) -> 1638.986 | E8: =IFERROR((Supuestos!$C$11+Supuestos!$C$12)/($B8*Supuestos!$C$6*(1-Supuestos!$C$7))/(1-E$4),0) -> 1815.4922 | F8: =IFERROR((Supuestos!$C$11+Supuestos!$C$12)/($B8*Supuestos!$C$6*(1-Supuestos!$C$7))/(1-F$4),0) -> 2034.6033 | G8: =IFERROR((Supuestos!$C$11+Supuestos!$C$12)/($B8*Supuestos!$C$6*(1-Supuestos!$C$7))/(1-G$4),0) -> 2360.1399
B9: 20 | C9: =IFERROR((Supuestos!$C$11+Supuestos!$C$12)/($B9*Supuestos!$C$6*(1-Supuestos!$C$7))/(1-C$4),0) -> 1180.0699 | D9: =IFERROR((Supuestos!$C$11+Supuestos!$C$12)/($B9*Supuestos!$C$6*(1-Supuestos!$C$7))/(1-D$4),0) -> 1311.1888 | E9: =IFERROR((Supuestos!$C$11+Supuestos!$C$12)/($B9*Supuestos!$C$6*(1-Supuestos!$C$7))/(1-E$4),0) -> 1452.3938 | F9: =IFERROR((Supuestos!$C$11+Supuestos!$C$12)/($B9*Supuestos!$C$6*(1-Supuestos!$C$7))/(1-F$4),0) -> 1627.6827 | G9: =IFERROR((Supuestos!$C$11+Supuestos!$C$12)/($B9*Supuestos!$C$6*(1-Supuestos!$C$7))/(1-G$4),0) -> 1888.1119
B12: Leer así: cada celda es la tarifa por hora que Adriana necesita cobrar para llegar a su ingreso objetivo con esas horas y ese margen. Menos horas disponibles obliga a cobrar más caro, no más barato — es el error más común al empezar de medio tiempo.

Sheet Matriz
A1: Matriz de servicios por nivel
A2: Qué entra en cada nivel. Esto es lo que va publicado en el sitio.
B4: Servicio | C4: Qué es | D4: START | E4: MANAGE | F4: PARTNER
B5: Supply chain health check | C5: Diagnóstico de 10–15 días | D5: Incluido | E5: Incluido | F5: Incluido
B6: Plan de importación | C6: Producto, origen, arancel, costo en destino | D6: Incluido | E6: Incluido | F6: Incluido
B7: Gestión de importaciones | C7: Coordinación de cada embarque de punta a punta | D7: — | E7: Incluido | F7: Incluido
B8: Revisión documental previa | C8: Antes de que embarque el proveedor | D8: — | E8: Incluido | F8: Incluido
B9: Coordinación de forwarder y agente | C9: Selección, comparación y auditoría | D9: — | E9: Incluido | F9: Incluido
B10: Cierre de expediente e indicadores | C10: Costo real por embarque, OTIF, incidencias | D10: — | E10: Incluido | F10: Incluido
B11: Optimización de cadena de suministro | C11: Búsqueda de fugas de costo | D11: Proyecto aparte | E11: Proyecto aparte | F11: Incluido
B12: Torre de control logística | C12: Monitoreo, ETA, retrasos, incidencias | D12: — | E12: Proyecto aparte | F12: Incluido
B13: Exportaciones | C13: Además de importaciones | D13: — | E13: — | F13: Incluido
B14: Logística de abastecimiento | C14: Gestión de proveedores y compras | D14: — | E14: — | F14: Incluido
B15: Cumplimiento y auditoría documental | C15: Trámites y expedientes ante revisión | D15: — | E15: — | F15: Incluido
... B18: Gerencia interina de logística | C18: 3 a 12 meses cubriendo la función | D18: Proyecto aparte | E18: Proyecto aparte | F18: Proyecto aparte
B20: PRECIO DE CADA NIVEL
B21: START | C21: Proyecto de precio fijo | D21: ='Bandas de precio'!E6 -> 54868.209
B22: MANAGE | C22: Iguala + fee por embarque (12 embarques/mes) | D22: ='Bandas de precio'!C16 -> 89967.725
B23: PARTNER | C23: Iguala mensual, contrato anual | D23: ='Bandas de precio'!E10 -> 68585.261
B25: PARTNER está en la matriz pero la hoja 'Capacidad' dice si cabe en las horas de Adriana. Publicar un nivel que no se puede sostener es peor que no ofrecerlo: el primer cliente que lo contrate se lleva la mala experiencia.

Sheet Validación de mercado
A1: Antes de publicar un precio
A2: El modelo da el piso. El mercado da el techo. Falta la mitad del dato.
B4: Este libro calcula lo que logistika NECESITA cobrar. No sabe lo que el mercado de Querétaro está dispuesto a pagar, porque nadie lo ha preguntado todavía. Sin este contraste, el riesgo no es cobrar caro: es cobrar barato y no enterarse.
B7: A quién preguntar | C7: Qué preguntar | D7: Precio que mencionó | E7: Fecha | F7: Fuente
B8: Un agente aduanal conocido | C8: Cuánto cobra un consultor externo que le audita al cliente
B9: Un ex-colega de Geodis o UTI | C9: Qué cobra hoy quien hace gestión de importaciones por fuera
B10: Un contacto en un parque industrial | C10: Qué presupuesto tienen para un diagnóstico externo
B11: Una empresa que ya dijo que no | C11: Qué le pareció caro y contra qué lo comparó
B12: Alguien del Foro de Logística de SEDESU | C12: Qué proveedores usan y en qué rango pagan
B14: Regla práctica: si nadie ha dicho que el precio le parece caro, está bajo. Un porcentaje sano de propuestas rechazadas por precio está entre el 20% y el 40%; con cero rechazos, se está dejando dinero en la mesa.
